 {
  "app-side-nav": {
    "wrapper": {
      "border": {
        "width": {
          "value": "1",
          "type": "size"
        },
        "color": {
          "value": "var(--token-color-palette-neutral-200)",
          "type": "color",
          "group": "components"
        }
      },
      "padding": {
        "horizontal": {
          "value": "16",
          "type": "size"
        },
        "vertical": {
          "value": "16",
          "type": "size"
        },
        "horizontal-minimized": {
          "value": "8",
          "type": "size"
        },
        "vertical-minimized": {
          "value": "22",
          "type": "size"
        }
      }
    },
    "toggle-button": {
      "border": {
        "radius": {
          "value": "5",
          "type": "size"
        }
      }
    },
    "header": {
      "home-link": {
        "padding": {
          "value": "4",
          "type": "size"
        },
        "logo-size": {
          "value": "48",
          "type": "size"
        },
        "logo-size-minimized": {
          "value": "32",
          "type": "size"
        }
      },
      "actions": {
        "spacing": {
          "value": "8",
          "type": "size"
        }
      }
    },
    "body": {
      "list": {
        "margin-vertical": {
          "value": "24",
          "type": "size"
        }
      },
      "list-item": {
        "height": {
          "value": "36",
          "type": "size"
        },
        "padding": {
          "horizontal": {
            "value": "8",
            "type": "size"
          },
          "vertical": {
            "value": "4",
            "type": "size"
          }
        },
        "spacing-vertical": {
          "value": "2",
          "type": "size"
        },
        "content-spacing-horizontal": {
          "value": "8",
          "type": "size"
        },
        "border-radius": {
          "value": "5",
          "type": "size"
        }
      }
    },
    "color": {
      "foreground": {
        "primary": {
          "value": "var(--token-color-foreground-primary)",
          "type": "color",
          "group": "components"
        },
        "strong": {
          "value": "var(--token-color-foreground-primary)",
          "type": "color",
          "group": "components"
        },
        "faint": {
          "value": "#8c909c",
          "type": "color",
          "group": "components"
        }
      },
      "surface": {
        "primary": {
          "value": "var(--token-color-surface-faint)",
          "type": "color",
          "group": "components"
        },
        "interactive-hover": {
          "value": "var(--token-color-surface-interactive-hover)",
          "type": "color",
          "group": "semantic"
        },
        "interactive-active": {
          "value": "var(--token-color-palette-neutral-300)",
          "type": "color",
          "group": "semantic"
        }
      }
    }
  }
}