{
  "reveal": {
    "padding": {
      "top:": {
        "$type": "dimension",
        "$value": "5",
        "unit": "px",
        "$modes": {
          "default": "5",
          "cds-g0": "{button.padding.vertical.medium}",
          "cds-g10":  "{button.padding.vertical.medium}",
          "cds-g90": "{button.padding.vertical.medium}",
          "cds-g100": "{button.padding.vertical.medium}"
        }
      },
      "right": {
        "$type": "dimension",
        "$value": "5",
        "unit": "px",
        "$modes": {
          "default": "5",
          "cds-g0": "16",
          "cds-g10": "16",
          "cds-g90": "16",
          "cds-g100": "16"
        }
      },
      "bottom": {
        "$type": "dimension",
        "$value": "5",
        "unit": "px",
        "$modes": {
          "default": "5",
          "cds-g0": "{button.padding.vertical.medium}",
          "cds-g10": "{button.padding.vertical.medium}",
          "cds-g90": "{button.padding.vertical.medium}",
          "cds-g100": "{button.padding.vertical.medium}"
        }
      },
      "left": {
        "$type": "dimension",
        "$value": "3",
        "unit": "px",
        "$modes": {
          "default": "3",
          "cds-g0": "16",
          "cds-g10": "16",
          "cds-g90": "16",
          "cds-g100": "16"
        }
      }
    }
  }
}
